kmsshademo/_init_.py
kmsshademo/hashingutils.py
kms_sha_aws-1.0.0.dist-info/METADATA
kms_sha_aws-1.0.0.dist-info/WHEEL
kms_sha_aws-1.0.0.dist-info/top_level.txt
kms_sha_aws-1.0.0.dist-info/RECORD
