Metadata-Version: 2.1
Name: kms-sha-aws
Version: 1.0.0
Summary: kms and hashing library
Home-page: UNKNOWN
Author: Nitish Chandna
License: MIT
Platform: UNKNOWN
